{
  "date": "2026-04-16",
  "saved_at": "2026-06-12T14:28:10.924735",
  "mode": "phase6b",
  "market_regime": "bull",
  "bull_strength": 0.9065,
  "portfolio": [
    {
      "stock_id": "300502",
      "weight": 0.203657,
      "score": 0.9893970791317737,
      "sector_id": 3
    },
    {
      "stock_id": "002463",
      "weight": 0.201343,
      "score": 0.9836838904736821,
      "sector_id": 1
    },
    {
      "stock_id": "000157",
      "weight": 0.200389,
      "score": 0.981309247093192,
      "sector_id": 1
    },
    {
      "stock_id": "600176",
      "weight": 0.200193,
      "score": 0.9808198428970072,
      "sector_id": 0
    },
    {
      "stock_id": "300394",
      "weight": 0.194417,
      "score": 0.9661804592571192,
      "sector_id": 3
    }
  ],
  "bull_top5": [
    "300502",
    "600176",
    "601898",
    "002466",
    "002463"
  ],
  "nonbull_top5": [
    "000157",
    "300014",
    "300124",
    "300498",
    "300476"
  ],
  "consensus_overlap": 0,
  "score_distribution": {
    "min": 0.00986243876424839,
    "max": 0.9893970791317737,
    "mean": 0.5017182130584192,
    "std": 0.27698367678145797
  },
  "sector_distribution": {
    "1": 2,
    "3": 2,
    "0": 1
  }
}