{
  "date": "2026-05-06",
  "saved_at": "2026-06-12T14:28:11.263921",
  "mode": "phase6b",
  "market_regime": "bull",
  "bull_strength": 1.0,
  "portfolio": [
    {
      "stock_id": "300502",
      "weight": 0.204148,
      "score": 0.9999999963362906,
      "sector_id": 3
    },
    {
      "stock_id": "601225",
      "weight": 0.202745,
      "score": 0.9965515868709499,
      "sector_id": 0
    },
    {
      "stock_id": "600176",
      "weight": 0.201352,
      "score": 0.9931034013803809,
      "sector_id": 0
    },
    {
      "stock_id": "002463",
      "weight": 0.197229,
      "score": 0.9827586177586876,
      "sector_id": 1
    },
    {
      "stock_id": "002028",
      "weight": 0.194527,
      "score": 0.9758620704310009,
      "sector_id": 1
    }
  ],
  "bull_top5": [
    "300502",
    "601225",
    "600176",
    "603296",
    "601898"
  ],
  "nonbull_top5": [
    "300274",
    "300033",
    "300059",
    "002384",
    "002028"
  ],
  "consensus_overlap": 0,
  "score_distribution": {
    "min": 0.0034483078584649106,
    "max": 0.9999999963362906,
    "mean": 0.5017241379310344,
    "std": 0.28867335835470864
  },
  "sector_distribution": {
    "1": 2,
    "0": 2,
    "3": 1
  }
}